[{"lat": 43.8036603, "lng": -79.2620294, "name": "Agincourt North"}, {"lat": 43.7895309, "lng": -79.2560622, "name": "Agincourt South-Malvern West"}, {"lat": 43.6035413, "lng": -79.5464093, "name": "Alderwood"}, {"lat": 43.6698329, "lng": -79.407585, "name": "Annex"}, {"lat": 43.7360646, "lng": -79.3593583, "name": "Banbury-Don Mills"}, {"lat": 43.7627405, "lng": -79.45632499999999, "name": "Bathurst Manor"}, {"lat": 43.6973925, "lng": -79.30599699999999, "name": "Bay Street Corridor"}, {"lat": 43.778243, "lng": -79.3827578, "name": "Bayview Village"}, {"lat": 43.7964111, "lng": -79.385975, "name": "Bayview Woods-Steeles"}, {"lat": 43.7301254, "lng": -79.4113072, "name": "Bedford Park-Nortown"}, {"lat": 43.6879613, "lng": -79.467576, "name": "Beechborough-Greenbrook"}, {"lat": 43.765434, "lng": -79.248935, "name": "Bendale"}, {"lat": 43.712217, "lng": -79.244001, "name": "Birchcliffe-Cliffside"}, {"lat": 43.6892304, "lng": -79.4956953, "name": "Black Creek"}, {"lat": 43.67586259999999, "lng": -79.3381065, "name": "Blake-Jones"}, {"lat": 43.705883, "lng": -79.45632499999999, "name": "Briar Hill-Belgravia"}, {"lat": 43.7359137, "lng": -79.3718986, "name": "Bridle Path-Sunnybrook-York Mills"}, {"lat": 43.6869346, "lng": -79.3550041, "name": "Broadview North"}, {"lat": 43.6990115, "lng": -79.4844499, "name": "Brookhaven-Amesbury"}, {"lat": 43.653203, "lng": -79.3811395, "name": "Cabbagetown-South St. James Town"}, {"lat": 43.6869159, "lng": -79.45632499999999, "name": "Caledonia-Fairbank"}, {"lat": 43.6780371, "lng": -79.4094439, "name": "Casa Loma"}, {"lat": 43.7834548, "lng": -79.149209, "name": "Centennial Scarborough"}, {"lat": 43.7120865, "lng": -79.2818728, "name": "Clairlea-Birchmount"}, {"lat": 43.74069799999999, "lng": -79.438824, "name": "Clanton Park"}, {"lat": 43.724917, "lng": -79.22632899999999, "name": "Cliffcrest"}, {"lat": 43.6750652, "lng": -79.42542809999999, "name": "Corso Italia-Davenport"}, {"lat": 43.6867771, "lng": -79.308071, "name": "Danforth"}, {"lat": 43.6860447, "lng": -79.311236, "name": "Danforth East York"}, {"lat": 43.7837792, "lng": -79.352188, "name": "Don Valley Village"}, {"lat": 43.7540011, "lng": -79.28211739999999, "name": "Dorset Park"}, {"lat": 43.6627589, "lng": -79.4424011, "name": "Dovercourt-Wallace Emerson-Junction"}, {"lat": 43.6558326, "lng": -79.4281914, "name": "Dufferin Grove"}, {"lat": 43.6779526, "lng": -79.30993699999999, "name": "East End-Danforth"}, {"lat": 43.667113, "lng": -79.527974, "name": "Edenbridge-Humber Valley"}, {"lat": 43.7248212, "lng": -79.30498399999999, "name": "Eglinton East"}, {"lat": 43.7236919, "lng": -79.5462943, "name": "Elms-Old Rexdale"}, {"lat": 43.718533, "lng": -79.4394459, "name": "Englemount-Lawrence"}, {"lat": 43.66250369999999, "lng": -79.5772008, "name": "Eringate-Centennial-West Deane"}, {"lat": 43.6309156, "lng": -79.5434841, "name": "Etobicoke West Mall"}, {"lat": 43.720507, "lng": -79.33877799999999, "name": "Flemingdon Park"}, {"lat": 43.70431800000001, "lng": -79.4267845, "name": "Forest Hill North"}, {"lat": 43.6927315, "lng": -79.4169356, "name": "Forest Hill South"}, {"lat": 43.653226, "lng": -79.3831843, "name": "Glenfield-Jane Heights"}, {"lat": 43.679545, "lng": -79.3268397, "name": "Greenwood-Coxwell"}, {"lat": 43.752743, "lng": -79.19277699999999, "name": "Guildwood"}, {"lat": 43.77178199999999, "lng": -79.352086, "name": "Henry Farm"}, {"lat": 43.6594968, "lng": -79.467576, "name": "High Park North"}, {"lat": 43.6494825, "lng": -79.4619506, "name": "High Park-Swansea"}, {"lat": 43.78658, "lng": -79.18829199999999, "name": "Highland Creek"}, {"lat": 43.804877, "lng": -79.35468999999999, "name": "Hillcrest Village"}, {"lat": 43.6963578, "lng": -79.527033, "name": "Humber Heights-Westmount"}, {"lat": 43.7601003, "lng": -79.5717846, "name": "Humber Summit"}, {"lat": 43.7421301, "lng": -79.5406738, "name": "Humbermede"}, {"lat": 43.6937813, "lng": -79.4281914, "name": "Humewood-Cedarvale"}, {"lat": 43.730824, "lng": -79.2739, "name": "Ionview"}, {"lat": 43.6309156, "lng": -79.5434841, "name": "Islington-City Centre West"}, {"lat": 43.666612, "lng": -79.468614, "name": "Junction Area"}, {"lat": 43.6879613, "lng": -79.467576, "name": "Keelesdale-Eglinton West"}, {"lat": 43.71666700000001, "lng": -79.259722, "name": "Kennedy Park"}, {"lat": 43.6534377, "lng": -79.4002009, "name": "Kensington-Chinatown"}, {"lat": 43.7005039, "lng": -79.5519144, "name": "Kingsview Village-The Westway"}, {"lat": 43.652674, "lng": -79.507194, "name": "Kingsway South"}, {"lat": 43.65604219999999, "lng": -79.4942916, "name": "Lambton Baby Point"}, {"lat": 43.796, "lng": -79.309, "name": "L'Amoreaux"}, {"lat": 43.7595964, "lng": -79.4225637, "name": "Lansing-Westgate"}, {"lat": 43.7232822, "lng": -79.3887901, "name": "Lawrence Park North"}, {"lat": 43.7153834, "lng": -79.4056784, "name": "Lawrence Park South"}, {"lat": 43.693193, "lng": -79.37223809999999, "name": "Leaside-Bennington"}, {"lat": 43.6463408, "lng": -79.4281914, "name": "Little Portugal"}, {"lat": 43.593421, "lng": -79.538164, "name": "Long Branch"}, {"lat": 43.80916, "lng": -79.22169, "name": "Malvern"}, {"lat": 43.7137562, "lng": -79.49007379999999, "name": "Maple Leaf"}, {"lat": 43.632036, "lng": -79.57513999999999, "name": "Markland Wood"}, {"lat": 43.8237331, "lng": -79.3070855, "name": "Milliken"}, {"lat": 43.6279083, "lng": -79.4756618, "name": "Mimico (includes Humber Bay Shores)"}, {"lat": 43.787, "lng": -79.206, "name": "Morningside"}, {"lat": 43.6547889, "lng": -79.3726025, "name": "Moss Park"}, {"lat": 43.687076, "lng": -79.48983299999999, "name": "Mount Dennis"}, {"lat": 43.7394164, "lng": -79.58843689999999, "name": "Mount Olive-Silverstone-Jamestown"}, {"lat": 43.7037974, "lng": -79.3831599, "name": "Mount Pleasant East"}, {"lat": 43.7048511, "lng": -79.3944199, "name": "Mount Pleasant West"}, {"lat": 43.6007776, "lng": -79.505257, "name": "New Toronto"}, {"lat": 43.790104, "lng": -79.4197497, "name": "Newtonbrook East"}, {"lat": 43.790104, "lng": -79.4197497, "name": "Newtonbrook West"}, {"lat": 43.6373829, "lng": -79.40849279999999, "name": "Niagara"}, {"lat": 43.669714, "lng": -79.353185, "name": "North Riverdale"}, {"lat": 43.6708666, "lng": -79.37330639999999, "name": "North St. James Town"}, {"lat": 43.696632, "lng": -79.282859, "name": "Oakridge"}, {"lat": 43.69008789999999, "lng": -79.4394459, "name": "Oakwood Village"}, {"lat": 43.7063972, "lng": -79.30993699999999, "name": "O'Connor-Parkview"}, {"lat": 43.6964049, "lng": -79.3296565, "name": "Old East York"}, {"lat": 43.65952799999999, "lng": -79.4169356, "name": "Palmerston-Little Italy"}, {"lat": 43.7553609, "lng": -79.3268397, "name": "Parkwoods-Donalda"}, {"lat": 43.7121365, "lng": -79.5238103, "name": "Pelmo Park-Humberlea"}, {"lat": 43.676404, "lng": -79.3578205, "name": "Playter Estates-Danforth"}, {"lat": 43.7848218, "lng": -79.3381065, "name": "Pleasant View"}, {"lat": 43.6688924, "lng": -79.5434841, "name": "Princess-Rosethorn"}, {"lat": 43.6603228, "lng": -79.3620439, "name": "Regent Park"}, {"lat": 43.7198568, "lng": -79.5705997, "name": "Rexdale-Kipling"}, {"lat": 43.6742272, "lng": -79.49850909999999, "name": "Rockcliffe-Smythe"}, {"lat": 43.6484365, "lng": -79.4506989, "name": "Roncesvalles"}, {"lat": 43.6877286, "lng": -79.37760329999999, "name": "Rosedale-Moore Park"}, {"lat": 43.804929, "lng": -79.165842, "name": "Rouge"}, {"lat": 43.6508634, "lng": -79.477651, "name": "Runnymede-Bloor West Village"}, {"lat": 43.641939, "lng": -79.4120889, "name": "Rustic"}, {"lat": 43.740615, "lng": -79.208887, "name": "Scarborough Village"}, {"lat": 43.643832, "lng": -79.442534, "name": "South Parkdale"}, {"lat": 43.669714, "lng": -79.353185, "name": "South Riverdale"}, {"lat": 43.7574902, "lng": -79.37471409999999, "name": "St.Andrew-Windfields"}, {"lat": 43.8155519, "lng": -79.3107689, "name": "Steeles"}, {"lat": 43.637238, "lng": -79.4835161, "name": "Stonegate-Queensway"}, {"lat": 43.788056, "lng": -79.301389, "name": "Tam O'Shanter-Sullivan"}, {"lat": 43.7280907, "lng": -79.2958408, "name": "Taylor-Massey"}, {"lat": 43.6673479, "lng": -79.29669299999999, "name": "The Beaches"}, {"lat": 43.7429033, "lng": -79.5712672, "name": "Thistletown-Beaumond Heights"}, {"lat": 43.7080032, "lng": -79.352188, "name": "Thorncliffe Park"}, {"lat": 43.6500371, "lng": -79.4169356, "name": "Trinity-Bellwoods"}, {"lat": 43.6628917, "lng": -79.39565640000001, "name": "University"}, {"lat": 43.7357352, "lng": -79.3124184, "name": "Victoria Village"}, {"lat": 43.6416481, "lng": -79.3779212, "name": "Waterfront Communities-The Island"}, {"lat": 43.769163, "lng": -79.182803, "name": "West Hill"}, {"lat": 43.7356492, "lng": -79.6258435, "name": "West Humber-Clairville"}, {"lat": 43.7764213, "lng": -79.4506989, "name": "Westminster-Branson"}, {"lat": 43.7002318, "lng": -79.51507810000001, "name": "Weston"}, {"lat": 43.6716304, "lng": -79.4577314, "name": "Weston-Pelham Park"}, {"lat": 43.7500715, "lng": -79.2958491, "name": "Wexford/Maryvale"}, {"lat": 43.7711708, "lng": -79.4197497, "name": "Willowdale East"}, {"lat": 43.7711708, "lng": -79.4197497, "name": "Willowdale West"}, {"lat": 43.6804443, "lng": -79.5659001, "name": "Willowridge-Martingrove-Richview"}, {"lat": 43.767528, "lng": -79.21772100000001, "name": "Woburn"}, {"lat": 43.6986022, "lng": -79.30960859999999, "name": "Woodbine Corridor"}, {"lat": 43.692177, "lng": -79.30993699999999, "name": "Woodbine-Lumsden"}, {"lat": 43.6748106, "lng": -79.4281914, "name": "Wychwood"}, {"lat": 43.70643099999999, "lng": -79.398642, "name": "Yonge-Eglinton"}, {"lat": 43.6898373, "lng": -79.398642, "name": "Yonge-St.Clair"}, {"lat": 43.7679803, "lng": -79.4872619, "name": "York University Heights"}, {"lat": 43.7101005, "lng": -79.4506989, "name": "Yorkdale-Glen Park"}]